chemaphy/__init__.py
chemaphy/about.py
chemaphy/example.py
chemaphy/meta.py
chemaphy/test.py
chemaphy-2.12.3.dist-info/LICENSE.txt
chemaphy-2.12.3.dist-info/METADATA
chemaphy-2.12.3.dist-info/WHEEL
chemaphy-2.12.3.dist-info/top_level.txt
chemaphy-2.12.3.dist-info/RECORD
